LICENSE
README.md
setup.py
steam_trader/__init__.py
steam_trader/__version__.py
steam_trader/constants.py
steam_trader/exceptions.py
steam_trader.egg-info/PKG-INFO
steam_trader.egg-info/SOURCES.txt
steam_trader.egg-info/dependency_links.txt
steam_trader.egg-info/requires.txt
steam_trader.egg-info/top_level.txt
steam_trader/api/__init__.py
steam_trader/api/_account.py
steam_trader/api/_base.py
steam_trader/api/_buy.py
steam_trader/api/_client.py
steam_trader/api/_client_async.py
steam_trader/api/_edit_item.py
steam_trader/api/_item_info.py
steam_trader/api/_misc.py
steam_trader/api/_offers.py
steam_trader/api/_p2p.py
steam_trader/api/_sale.py
steam_trader/api/_trade.py
steam_trader/api/ext/__init__.py
steam_trader/api/ext/_client_async_ext.py
steam_trader/api/ext/_client_ext.py
steam_trader/api/ext/_misc.py
steam_trader/web/__init__.py
steam_trader/web/_base.py
steam_trader/web/_client.py
steam_trader/web/_client_async.py
steam_trader/web/_dataclasses.py