Metadata-Version: 2.1
Name: steam-trader
Version: 1.0.1
Summary: Неофициальная Python библиотека для работы с API сервиса Steam-Trader.
Home-page: https://github.com/Lemon4ksan/SteamTrader-Wrapper
Author: Lemon4ksan (Bananchiki)
Author-email: senya20151718@gmail.com
License: BSD License
Project-URL: Документация, https://lemon4ksan.github.io/steam-trader/
Keywords: python steam trader api wrapper library client питон пайтон стим трейдер апи обёртка библиотека клиент
Classifier: Development Status :: 5 - Production/Stable
Classifier: Natural Language :: Russian
Classifier: Intended Audience :: Developers
Classifier: License :: OSI Approved :: BSD License
Classifier: Operating System :: OS Independent
Classifier: Topic :: Internet
Classifier: Topic :: Software Development :: Libraries
Classifier: Topic :: Software Development :: Libraries :: Python Modules
Classifier: Topic :: Software Development :: Libraries :: Application Frameworks
Classifier: Programming Language :: Python
Classifier: Programming Language :: Python :: 3.12
Classifier: Programming Language :: Python :: 3.13
Classifier: Programming Language :: Python :: Implementation
Classifier: Programming Language :: Python :: Implementation :: CPython
Classifier: Programming Language :: Python :: Implementation :: PyPy
Requires-Python: >=3.12
License-File: LICENSE
